README
setup.cfg
setup.py
relevanced_client/__init__.py
relevanced_client/client.py
relevanced_client/version.py
relevanced_client.egg-info/PKG-INFO
relevanced_client.egg-info/SOURCES.txt
relevanced_client.egg-info/dependency_links.txt
relevanced_client.egg-info/pbr.json
relevanced_client.egg-info/requires.txt
relevanced_client.egg-info/top_level.txt
relevanced_client.egg-info/zip-safe
relevanced_client/gen_py/__init__.py
relevanced_client/gen_py/RelevancedProtocol/Relevanced.py
relevanced_client/gen_py/RelevancedProtocol/__init__.py
relevanced_client/gen_py/RelevancedProtocol/constants.py
relevanced_client/gen_py/RelevancedProtocol/ttypes.py