Metadata-Version: 1.0
Name: relevanced-client
Version: 0.9.2
Summary: Python client for relevanced-server.
Home-page: http://www.relevanced.org
Author: Scott Ivey
Author-email: scott.ivey@gmail.com
License: UNKNOWN
Platform: UNKNOWN
